{"type":"Feature","geometry":{"type":"Polygon","coordinates":[[[36.4295,14.4221],[36.3232,14.8225],[36.7539,16.2919],[36.8525,16.9565],[37.1675,17.2631],[37.904,17.4275],[38.4101,17.9983],[38.9906,16.8406],[39.2661,15.9227],[39.8143,15.4356],[41.1793,14.4911],[41.735,13.921],[42.2768,13.344],[42.5896,13.0004],[43.0812,12.6996],[42.7796,12.4554],[42.3516,12.5422],[42.0097,12.8658],[41.5986,13.4521],[41.1552,13.7733],[40.8966,14.1186],[40.0263,14.5196],[39.3406,14.5315],[39.0994,14.7406],[38.513,14.5055],[37.9061,14.9594],[37.5938,14.2131],[36.4295,14.4221]]]},"id":"232","properties":{"featurecla":"Admin-0 country","scalerank":1,"labelrank":4,"sovereignt":"Eritrea","sov_a3":"ERI","adm0_dif":0,"level":2,"type":"Sovereign country","admin":"Eritrea","adm0_a3":"ERI","geou_dif":0,"geounit":"Eritrea","gu_a3":"ERI","su_dif":0,"subunit":"Eritrea","su_a3":"ERI","brk_diff":0,"name":"Eritrea","name_long":"Eritrea","brk_a3":"ERI","brk_name":"Eritrea","brk_group":null,"abbrev":"Erit.","postal":"ER","formal_en":"State of Eritrea","formal_fr":null,"name_ciawf":"Eritrea","note_adm0":null,"note_brk":null,"name_sort":"Eritrea","name_alt":null,"mapcolor7":3,"mapcolor8":1,"mapcolor9":2,"mapcolor13":12,"pop_est":5918919,"pop_rank":13,"gdp_md_est":9169,"pop_year":2017,"lastcensus":1984,"gdp_year":2016,"economy":"7. Least developed region","income_grp":"5. Low income","wikipedia":-99,"fips_10_":"ER","iso_a2":"ER","iso_a3":"ERI","iso_a3_eh":"ERI","iso_n3":"232","un_a3":"232","wb_a2":"ER","wb_a3":"ERI","woe_id":23424806,"woe_id_eh":23424806,"woe_note":"Exact WOE match as country","adm0_a3_is":"ERI","adm0_a3_us":"ERI","adm0_a3_un":-99,"adm0_a3_wb":-99,"continent":"Africa","region_un":"Africa","subregion":"Eastern Africa","region_wb":"Sub-Saharan Africa","name_len":7,"long_len":7,"abbrev_len":5,"tiny":-99,"homepart":1,"min_zoom":0,"min_label":4,"max_label":9,"ne_id":1159320581,"wikidataid":"Q986","name_ar":"إرتريا","name_bn":"ইরিত্রিয়া","name_de":"Eritrea","name_en":"Eritrea","name_es":"Eritrea","name_fr":"Érythrée","name_el":"Ερυθραία","name_hi":"इरित्रिया","name_hu":"Eritrea","name_id":"Eritrea","name_it":"Eritrea","name_ja":"エリトリア","name_ko":"에리트레아","name_nl":"Eritrea","name_pl":"Erytrea","name_pt":"Eritreia","name_ru":"Эритрея","name_sv":"Eritrea","name_tr":"Eritre","name_vi":"Eritrea","name_zh":"厄立特里亚","fill":"#001aff"}}