{"type":"Feature","geometry":{"type":"Polygon","coordinates":[[[104.3343,10.4865],[105.1999,10.8893],[106.2497,10.9618],[105.8105,11.5676],[107.4914,12.3372],[107.6145,13.5355],[107.3827,14.2024],[107.5645,15.2022],[107.3127,15.9085],[106.556,16.6043],[105.9258,17.4853],[105.0946,18.667],[103.8965,19.2652],[104.1834,19.6247],[104.8226,19.8866],[104.435,20.7587],[103.2039,20.7666],[102.7549,21.6751],[102.1704,22.4648],[102.707,22.7088],[103.5045,22.7038],[104.4769,22.8192],[105.3292,23.3521],[105.8112,22.9769],[106.7254,22.7943],[106.5673,22.2182],[107.0434,21.8119],[108.0502,21.5524],[106.7151,20.6969],[105.8817,19.7521],[105.662,19.0582],[106.4268,18.0041],[107.362,16.6975],[108.2695,16.0797],[108.8771,15.2767],[109.3353,13.426],[109.2001,11.6669],[108.3661,11.0083],[107.2209,10.3645],[106.4051,9.5308],[105.1583,8.5998],[104.7952,9.241],[105.0762,9.9185],[104.3343,10.4865]]]},"id":"704","properties":{"featurecla":"Admin-0 country","scalerank":1,"labelrank":2,"sovereignt":"Vietnam","sov_a3":"VNM","adm0_dif":0,"level":2,"type":"Sovereign country","admin":"Vietnam","adm0_a3":"VNM","geou_dif":0,"geounit":"Vietnam","gu_a3":"VNM","su_dif":0,"subunit":"Vietnam","su_a3":"VNM","brk_diff":0,"name":"Vietnam","name_long":"Vietnam","brk_a3":"VNM","brk_name":"Vietnam","brk_group":null,"abbrev":"Viet.","postal":"VN","formal_en":"Socialist Republic of Vietnam","formal_fr":null,"name_ciawf":"Vietnam","note_adm0":null,"note_brk":null,"name_sort":"Vietnam","name_alt":null,"mapcolor7":5,"mapcolor8":6,"mapcolor9":5,"mapcolor13":4,"pop_est":96160163,"pop_rank":16,"gdp_md_est":594900,"pop_year":2017,"lastcensus":2009,"gdp_year":2016,"economy":"5. Emerging region: G20","income_grp":"4. Lower middle income","wikipedia":-99,"fips_10_":"VM","iso_a2":"VN","iso_a3":"VNM","iso_a3_eh":"VNM","iso_n3":"704","un_a3":"704","wb_a2":"VN","wb_a3":"VNM","woe_id":23424984,"woe_id_eh":23424984,"woe_note":"Exact WOE match as country","adm0_a3_is":"VNM","adm0_a3_us":"VNM","adm0_a3_un":-99,"adm0_a3_wb":-99,"continent":"Asia","region_un":"Asia","subregion":"South-Eastern Asia","region_wb":"East Asia & Pacific","name_len":7,"long_len":7,"abbrev_len":5,"tiny":2,"homepart":1,"min_zoom":0,"min_label":2,"max_label":7,"ne_id":1159321417,"wikidataid":"Q881","name_ar":"فيتنام","name_bn":"ভিয়েতনাম","name_de":"Vietnam","name_en":"Vietnam","name_es":"Vietnam","name_fr":"Viêt Nam","name_el":"Βιετνάμ","name_hi":"वियतनाम","name_hu":"Vietnám","name_id":"Vietnam","name_it":"Vietnam","name_ja":"ベトナム","name_ko":"베트남","name_nl":"Vietnam","name_pl":"Wietnam","name_pt":"Vietname","name_ru":"Вьетнам","name_sv":"Vietnam","name_tr":"Vietnam","name_vi":"Việt Nam","name_zh":"越南","fill":"#ff00e6"}}